FunGUI/FunGUI.py
FunGUI/FunGUI.pyw
FunGUI/__init__.py
FunGUI/stock_analysis.py
FunGUI/stock_analysis_for_GUI.py
FunGUI/test_print.py
FunGUI/test_sin_plot.py
FunGUI/title.png
FunGUI-0.1.2.dist-info/LICENSE.txt
FunGUI-0.1.2.dist-info/METADATA
FunGUI-0.1.2.dist-info/WHEEL
FunGUI-0.1.2.dist-info/top_level.txt
FunGUI-0.1.2.dist-info/RECORD
